fastapi_blocks_registry-0.2.16.dist-info/licenses/LICENSE
fastapi_registry/__init__.py
fastapi_registry/cli.py
fastapi_registry/registry.json
fastapi_registry/core/__init__.py
fastapi_registry/core/file_utils.py
fastapi_registry/core/installer.py
fastapi_registry/core/project_initializer.py
fastapi_registry/core/registry_manager.py
fastapi_registry/example_project/.flake8
fastapi_registry/example_project/.gitignore
fastapi_registry/example_project/.pylintrc
fastapi_registry/example_project/cli.py
fastapi_registry/example_project/main.py
fastapi_registry/example_project/manage.py
fastapi_registry/example_project/pyproject.toml
fastapi_registry/example_project/requirements.txt
fastapi_registry/example_project/__pycache__/main.cpython-312.pyc
fastapi_registry/example_project/app/__init__.py
fastapi_registry/example_project/app/__pycache__/__init__.cpython-312.pyc
fastapi_registry/example_project/app/api/__init__.py
fastapi_registry/example_project/app/api/router.py
fastapi_registry/example_project/app/api/__pycache__/__init__.cpython-312.pyc
fastapi_registry/example_project/app/api/__pycache__/router.cpython-312.pyc
fastapi_registry/example_project/app/common/__init__.py
fastapi_registry/example_project/app/common/constants.py
fastapi_registry/example_project/app/common/pagination.py
fastapi_registry/example_project/app/common/search.py
fastapi_registry/example_project/app/common/utils.py
fastapi_registry/example_project/app/common/__pycache__/__init__.cpython-312.pyc
fastapi_registry/example_project/app/common/__pycache__/constants.cpython-312.pyc
fastapi_registry/example_project/app/common/__pycache__/pagination.cpython-312.pyc
fastapi_registry/example_project/app/common/__pycache__/search.cpython-312.pyc
fastapi_registry/example_project/app/common/__pycache__/utils.cpython-312.pyc
fastapi_registry/example_project/app/core/__init__.py
fastapi_registry/example_project/app/core/app_factory.py
fastapi_registry/example_project/app/core/config.py
fastapi_registry/example_project/app/core/database.py
fastapi_blocks_registry-0.2.16.dist-info/METADATA
fastapi_blocks_registry-0.2.16.dist-info/WHEEL
fastapi_blocks_registry-0.2.16.dist-info/entry_points.txt
fastapi_blocks_registry-0.2.16.dist-info/top_level.txt
fastapi_blocks_registry-0.2.16.dist-info/RECORD
