Metadata-Version: 2.4
Name: fastapi-blocks-registry
Version: 0.2.16
Summary: A modular scaffolding system for FastAPI backends
Author-email: Jan Madeyski <jan.madeyski@gmail.com>
License: MIT
Project-URL: Homepage, https://github.com/jm-sky/fastapi-blocks-registry
Project-URL: Documentation, https://github.com/jm-sky/fastapi-blocks-registry#readme
Project-URL: Repository, https://github.com/jm-sky/fastapi-blocks-registry
Project-URL: Issues, https://github.com/jm-sky/fastapi-blocks-registry/issues
Keywords: fastapi,scaffolding,cli,backend,boilerplate,templates,code-generator
Classifier: Development Status :: 3 - Alpha
Classifier: Intended Audience :: Developers
Classifier: License :: OSI Approved :: MIT License
Classifier: Programming Language :: Python :: 3
Classifier: Programming Language :: Python :: 3.12
Classifier: Framework :: FastAPI
Classifier: Topic :: Software Development :: Code Generators
Classifier: Topic :: Software Development :: Libraries :: Application Frameworks
Requires-Python: >=3.12
License-File: LICENSE
Requires-Dist: typer>=0.20.0
Requires-Dist: rich>=14.2.0
Requires-Dist: pydantic>=2.12.0
Requires-Dist: pydantic-settings>=2.11.0
Provides-Extra: dev
Requires-Dist: pytest>=8.4.2; extra == "dev"
Requires-Dist: pytest-cov>=6.0.0; extra == "dev"
Requires-Dist: black>=24.10.0; extra == "dev"
Requires-Dist: ruff>=0.8.4; extra == "dev"
Requires-Dist: mypy>=1.14.0; extra == "dev"
Dynamic: license-file
